loom/__init__.py
loom/database.py
loom/dataset.py
loom/exception.py
loom/datastructure/__init__.py
loom/datastructure/hashtable.py
loom_db-0.0.0.dist-info/METADATA
loom_db-0.0.0.dist-info/WHEEL
loom_db-0.0.0.dist-info/top_level.txt
loom_db-0.0.0.dist-info/RECORD
